en_pyssant/__init__.py
en_pyssant/_board.py
en_pyssant/_cli.py
en_pyssant/_core.py
en_pyssant/_game.py
en_pyssant/_position.py
en_pyssant/_util.py
en_pyssant/engine.py
en_pyssant/mcts.pickle
en_pyssant/rules.py
en_pyssant-0.2.0.dist-info/DESCRIPTION.rst
en_pyssant-0.2.0.dist-info/METADATA
en_pyssant-0.2.0.dist-info/RECORD
en_pyssant-0.2.0.dist-info/WHEEL
en_pyssant-0.2.0.dist-info/entry_points.txt
en_pyssant-0.2.0.dist-info/metadata.json
en_pyssant-0.2.0.dist-info/top_level.txt
