Metadata-Version: 2.0
Name: en-pyssant
Version: 0.2.0
Summary: En Pyssant is a chess implementation and engine
Home-page: https://gitlab.com/carmenbianca/en-pyssant
Author: Carmen Bianca Bakker
Author-email: carmen@carmenbianca.eu
License: GPL-3.0+
Platform: UNKNOWN
Classifier: Development Status :: 2 - Pre-Alpha
Classifier: License :: OSI Approved :: GNU General Public License v3 or later (GPLv3+)
Classifier: Programming Language :: Python :: 3
Classifier: Programming Language :: Python :: 3.4
Classifier: Programming Language :: Python :: 3.5
Classifier: Programming Language :: Python :: 3.6
